snake_opencv/__init__.py
snake_opencv/core/__init__.py
snake_opencv/core/binding.py
snake_opencv/core/const.py
snake_opencv/dnn/__init__.py
snake_opencv/dnn/binding.py
snake_opencv/dnn/const.py
snake_opencv/highgui/__init__.py
snake_opencv/highgui/binding.py
snake_opencv/highgui/const.py
snake_opencv/imgcodecs/__init__.py
snake_opencv/imgcodecs/binding.py
snake_opencv/imgcodecs/const.py
snake_opencv/imgproc/__init__.py
snake_opencv/imgproc/binding.py
snake_opencv/imgproc/const.py
snake_opencv/photo/__init__.py
snake_opencv/photo/binding.py
snake_opencv/photo/const.py
snake_opencv/py.typed
snake_opencv/videoio/__init__.py
snake_opencv/videoio/binding.py
snake_opencv/videoio/const.py
snake_opencv-0.1.7.dist-info/LICENSE
snake_opencv-0.1.7.dist-info/METADATA
snake_opencv-0.1.7.dist-info/WHEEL
snake_opencv-0.1.7.dist-info/RECORD
