Metadata-Version: 2.1
Name: snake-opencv
Version: 0.1.7
Summary: Snake case opencv with type annotations
Home-page: https://github.com/cospectrum/snake-opencv
License: Apache-2.0
Author: cospectrum
Author-email: severinalexeyv@gmail.com
Requires-Python: >=3.8.1,<4.0.0
Classifier: License :: OSI Approved :: Apache Software License
Classifier: Programming Language :: Python :: 3
Classifier: Programming Language :: Python :: 3.9
Classifier: Programming Language :: Python :: 3.10
Classifier: Programming Language :: Python :: 3.11
Requires-Dist: opencv-python (>=4.0,<5.0)
Requires-Dist: typing-extensions (>=4.5.0,<5.0.0)
Project-URL: Repository, https://github.com/cospectrum/snake-opencv
